bas/__init__.py
bas/bas.py
bas/bbas.py
bas/demo.py
bas/rbas.py
pybas-0.0.2.dist-info/DESCRIPTION.rst
pybas-0.0.2.dist-info/METADATA
pybas-0.0.2.dist-info/RECORD
pybas-0.0.2.dist-info/WHEEL
pybas-0.0.2.dist-info/metadata.json
pybas-0.0.2.dist-info/top_level.txt
