Metadata-Version: 2.0
Name: pybas
Version: 0.0.2
Summary: Beetle Antennae Search Algorithm for python 3.x
Home-page: UNKNOWN
Author: A.Star
Author-email: astar@snowland.ltd
License: BSD License
Platform: all
Classifier: Development Status :: 4 - Beta
Classifier: Operating System :: OS Independent
Classifier: Intended Audience :: Developers
Classifier: License :: OSI Approved :: BSD License
Classifier: Programming Language :: Python
Classifier: Programming Language :: Python :: Implementation
Classifier: Programming Language :: Python :: 2
Classifier: Programming Language :: Python :: 2.7
Classifier: Programming Language :: Python :: 3
Classifier: Programming Language :: Python :: 3.4
Classifier: Programming Language :: Python :: 3.5
Classifier: Programming Language :: Python :: 3.6
Classifier: Programming Language :: Python :: 3.7
Classifier: Topic :: Software Development :: Libraries
Requires-Dist: snowland-algorithm (>=0.0.7)
Requires-Dist: numpy (>=1.0.0)
Requires-Dist: astartool (>=0.0.2)
